assem/__init__.py
assem/auth.py
assem/exceptions.py
assem/service_mode.py
assem/utils.py
assem-0.3.1.dist-info/licenses/LICENSE
assem-0.3.1.dist-info/METADATA
assem-0.3.1.dist-info/WHEEL
assem-0.3.1.dist-info/top_level.txt
assem-0.3.1.dist-info/RECORD
