Metadata-Version: 2.4
Name: assem
Version: 0.3.1
Summary: A flexible and secure JWT authentication framework for FastAPI applications
Home-page: https://github.com/BagzhanKarl/assem-auth
Author: Bagzhan Karl
Author-email: bagzhankarl@gmail.com
Project-URL: Bug Tracker, https://github.com/BagzhanKarl/assem-auth/issues
Project-URL: Documentation, https://github.com/BagzhanKarl/assem-auth
Project-URL: Source Code, https://github.com/BagzhanKarl/assem-auth
Keywords: auth,authentication,FastAPI,OAuth2,JWT,security,Fastapi jwt
Classifier: Programming Language :: Python :: 3
Classifier: Programming Language :: Python :: 3.7
Classifier: Programming Language :: Python :: 3.8
Classifier: Programming Language :: Python :: 3.9
Classifier: Programming Language :: Python :: 3.10
Classifier: License :: OSI Approved :: MIT License
Classifier: Operating System :: OS Independent
Classifier: Framework :: FastAPI
Classifier: Intended Audience :: Developers
Classifier: Topic :: Software Development :: Libraries :: Python Modules
Classifier: Topic :: Security :: Cryptography
Requires-Python: >=3.10
License-File: LICENSE
Requires-Dist: fastapi>=0.68.0
Requires-Dist: pydantic>=1.8.0
Requires-Dist: pyjwt
Requires-Dist: starlette>=0.14.2
Provides-Extra: dev
Requires-Dist: pytest>=6.0.0; extra == "dev"
Requires-Dist: pytest-asyncio>=0.15.0; extra == "dev"
Requires-Dist: black>=21.5b2; extra == "dev"
Requires-Dist: isort>=5.9.1; extra == "dev"
Requires-Dist: mypy>=0.910; extra == "dev"
Requires-Dist: flake8>=3.9.2; extra == "dev"
Requires-Dist: uvicorn>=0.14.0; extra == "dev"
Dynamic: author
Dynamic: author-email
Dynamic: classifier
Dynamic: description
Dynamic: description-content-type
Dynamic: home-page
Dynamic: keywords
Dynamic: license-file
Dynamic: project-url
Dynamic: provides-extra
Dynamic: requires-dist
Dynamic: requires-python
Dynamic: summary
